pythonds/__init__.py
pythonds/basic/__init__.py
pythonds/basic/deque.py
pythonds/basic/queue.py
pythonds/basic/stack.py
pythonds/graphs/__init__.py
pythonds/graphs/adjGraph.py
pythonds/graphs/priorityQueue.py
pythonds/trees/__init__.py
pythonds/trees/balance.py
pythonds/trees/binaryTree.py
pythonds/trees/binheap.py
pythonds/trees/bst.py
pythonds-1.2.0.dist-info/DESCRIPTION.rst
pythonds-1.2.0.dist-info/METADATA
pythonds-1.2.0.dist-info/metadata.json
pythonds-1.2.0.dist-info/RECORD
pythonds-1.2.0.dist-info/top_level.txt
pythonds-1.2.0.dist-info/WHEEL
